aimrobot/Model.py
aimrobot/Reader.py
aimrobot/__init__.py
aimrobot/main.py
aimrobot-0.0.1.dist-info/LICENSE
aimrobot-0.0.1.dist-info/METADATA
aimrobot-0.0.1.dist-info/WHEEL
aimrobot-0.0.1.dist-info/top_level.txt
aimrobot-0.0.1.dist-info/RECORD
