Metadata-Version: 2.1
Name: aimrobot
Version: 0.0.1
Summary: A library to run Robotic Assembly Digital Model (RADM) files directly on Universal Robots.
Home-page: https://github.com/ALharchi/aimrobot
Author: A.L
Author-email: alha@kadk.dk
License: UNKNOWN
Platform: UNKNOWN
Classifier: Programming Language :: Python :: 3
Classifier: License :: OSI Approved :: GNU General Public License v3 (GPLv3)
Classifier: Operating System :: OS Independent
Requires-Python: >=3.6
